{"nodes": [{"id": "src_lib_baileys_ts", "label": "baileys.ts", "file_type": "code", "source_file": "src\\lib\\baileys.ts", "source_location": "L1"}, {"id": "baileys_createwhatsappsession", "label": "createWhatsAppSession()", "file_type": "code", "source_file": "src\\lib\\baileys.ts", "source_location": "L12"}, {"id": "baileys_getwhatsappsession", "label": "getWhatsAppSession()", "file_type": "code", "source_file": "src\\lib\\baileys.ts", "source_location": "L23"}, {"id": "baileys_sendwhatsappmessage", "label": "sendWhatsAppMessage()", "file_type": "code", "source_file": "src\\lib\\baileys.ts", "source_location": "L27"}], "edges": [{"source": "src_lib_baileys_ts", "target": "zod", "relation": "imports_from", "confidence": "EXTRACTED", "source_file": "src\\lib\\baileys.ts", "source_location": "L1", "weight": 1.0}, {"source": "src_lib_baileys_ts", "target": "types", "relation": "imports_from", "confidence": "EXTRACTED", "source_file": "src\\lib\\baileys.ts", "source_location": "L3", "weight": 1.0}, {"source": "src_lib_baileys_ts", "target": "baileys_createwhatsappsession", "relation": "contains", "confidence": "EXTRACTED", "source_file": "src\\lib\\baileys.ts", "source_location": "L12", "weight": 1.0}, {"source": "src_lib_baileys_ts", "target": "baileys_getwhatsappsession", "relation": "contains", "confidence": "EXTRACTED", "source_file": "src\\lib\\baileys.ts", "source_location": "L23", "weight": 1.0}, {"source": "src_lib_baileys_ts", "target": "baileys_sendwhatsappmessage", "relation": "contains", "confidence": "EXTRACTED", "source_file": "src\\lib\\baileys.ts", "source_location": "L27", "weight": 1.0}, {"source": "baileys_getwhatsappsession", "target": "baileys_createwhatsappsession", "relation": "calls", "confidence": "EXTRACTED", "source_file": "src\\lib\\baileys.ts", "source_location": "L24", "weight": 1.0}]}