{"nodes": [{"id": "src_components_layout_dashboard_shell_tsx", "label": "dashboard-shell.tsx", "file_type": "code", "source_file": "src\\components\\layout\\dashboard-shell.tsx", "source_location": "L1"}, {"id": "dashboard_shell_dashboardshell", "label": "DashboardShell()", "file_type": "code", "source_file": "src\\components\\layout\\dashboard-shell.tsx", "source_location": "L29"}], "edges": [{"source": "src_components_layout_dashboard_shell_tsx", "target": "link", "relation": "imports_from", "confidence": "EXTRACTED", "source_file": "src\\components\\layout\\dashboard-shell.tsx", "source_location": "L2", "weight": 1.0}, {"source": "src_components_layout_dashboard_shell_tsx", "target": "navigation", "relation": "imports_from", "confidence": "EXTRACTED", "source_file": "src\\components\\layout\\dashboard-shell.tsx", "source_location": "L3", "weight": 1.0}, {"source": "src_components_layout_dashboard_shell_tsx", "target": "react", "relation": "imports_from", "confidence": "EXTRACTED", "source_file": "src\\components\\layout\\dashboard-shell.tsx", "source_location": "L4", "weight": 1.0}, {"source": "src_components_layout_dashboard_shell_tsx", "target": "lucide_react", "relation": "imports_from", "confidence": "EXTRACTED", "source_file": "src\\components\\layout\\dashboard-shell.tsx", "source_location": "L5", "weight": 1.0}, {"source": "src_components_layout_dashboard_shell_tsx", "target": "src_components_layout_bottom_nav", "relation": "imports_from", "confidence": "EXTRACTED", "source_file": "src\\components\\layout\\dashboard-shell.tsx", "source_location": "L14", "weight": 1.0}, {"source": "src_components_layout_dashboard_shell_tsx", "target": "dashboard_shell_dashboardshell", "relation": "contains", "confidence": "EXTRACTED", "source_file": "src\\components\\layout\\dashboard-shell.tsx", "source_location": "L29", "weight": 1.0}]}